summary.rst
flask_blocks-1.0.23.dist-info/DESCRIPTION.rst
flask_blocks-1.0.23.dist-info/METADATA
flask_blocks-1.0.23.dist-info/RECORD
flask_blocks-1.0.23.dist-info/WHEEL
flask_blocks-1.0.23.dist-info/metadata.json
flask_blocks-1.0.23.dist-info/top_level.txt
flaskblocks/__init__.py
flaskblocks/auth/__init__.py
flaskblocks/auth/init.py
flaskblocks/auth/blueprints/__init__.py
flaskblocks/auth/blueprints/multiauth.py
flaskblocks/auth/providers/__init__.py
flaskblocks/auth/providers/facebook_oauth2.py
flaskblocks/auth/providers/google_oauth2.py
flaskblocks/auth/providers/oauth2.py
flaskblocks/auth/providers/stub.py
flaskblocks/minify/__init__.py
flaskblocks/minify/exceptions.py
flaskblocks/minify/htmlmin.py
flaskblocks/minify/pelicandd.py
