Metadata-Version: 2.0
Name: flask-blocks
Version: 1.0.23
Summary: The common blocks which solve common problems encountered when creating Flask applications.
Home-page: http://go.pelicandd.com/n/flaskblocks
Author: Arseni Mourzenko
Author-email: arseni.mourzenko@pelicandd.com
License: MIT
Keywords: flask
Platform: UNKNOWN
